weathercom/WeatherDetails.py
weathercom/__init__.py
weathercom/weatherFunc.py
weathercom-1.0.5.dist-info/LICENSE.txt
weathercom-1.0.5.dist-info/METADATA
weathercom-1.0.5.dist-info/WHEEL
weathercom-1.0.5.dist-info/top_level.txt
weathercom-1.0.5.dist-info/RECORD
