Metadata-Version: 2.1
Name: weathercom
Version: 1.0.5
Summary: A Python package to get weather reports for any location from weather.com. API for weather.com
Home-page: https://github.com/prashanth-p/weathercom/
Author: Prashanth Pradeep
Author-email: prashanth.pradeep96@gmail.com
License: MIT
Keywords: weather,weather.com,python weather,weatherpy,yahoo weather,google weather,open weather python,weather api,weather api json
Platform: UNKNOWN
Classifier: License :: OSI Approved :: MIT License
Classifier: Programming Language :: Python :: 3
Classifier: Programming Language :: Python :: 3.4
Classifier: Programming Language :: Python :: 3.5
Classifier: Programming Language :: Python :: 3.6
Classifier: Programming Language :: Python :: 3.7
